genomeocean/__init__.py
genomeocean/dnautils.py
genomeocean/generation.py
genomeocean/genomescan.py
genomeocean/llm_utils.py
genomeocean-0.5.0.dist-info/LICENSE
genomeocean-0.5.0.dist-info/METADATA
genomeocean-0.5.0.dist-info/WHEEL
genomeocean-0.5.0.dist-info/top_level.txt
genomeocean-0.5.0.dist-info/RECORD
