Metadata-Version: 2.1
Name: genomeocean
Version: 0.5.0
Summary: A Python library for GenomeOcean inference and fine-tuning.
Home-page: https://github.com/jgi-genomeocean/genomeocean
Author: Zhong Wang
Author-email: zhongwang@lbl.gov
Classifier: Programming Language :: Python :: 3.8
Classifier: Programming Language :: Python :: 3.9
Classifier: Programming Language :: Python :: 3.10
Classifier: Programming Language :: Python :: 3.11
Classifier: Operating System :: OS Independent
Requires-Python: >=3.8
License-File: LICENSE
Requires-Dist: numpy==1.26.4
Requires-Dist: torch==2.4.0
Requires-Dist: biopython==1.83
Requires-Dist: einops==0.7.0
Requires-Dist: transformers==4.44.2
Requires-Dist: vllm==0.6.1.post2
Requires-Dist: flash-attn==2.6.3
Requires-Dist: triton==3.0.0
Requires-Dist: tqdm==4.66.4
Requires-Dist: scikit-learn==1.5.0
Requires-Dist: pyrodigal==3.6.3
Requires-Dist: peft==0.14.0
Requires-Dist: wandb==0.19.4
